{
  "$schema": "https://mintlify.com/docs.json",
  "name": "Substratum",
  "theme": "aspen",
  "colors": {
    "primary": "#478e33",
    "light": "#533a07",
    "dark": "#478e33"
  },
  "favicon": "https://media.brand.dev/d98cde87-4552-4c42-9090-f6a775abf765.png",
  "logo": {
    "light": "https://media.brand.dev/d98cde87-4552-4c42-9090-f6a775abf765.png",
    "dark": "https://media.brand.dev/d98cde87-4552-4c42-9090-f6a775abf765.png"
  },
  "navbar": {
    "primary": {
      "type": "github",
      "href": "https://github.com/DeathShadez/Substratum"
    }
  },
  "footer": {
    "socials": {
      "github": "https://github.com/DeathShadez/Substratum"
    }
  },
  "navigation": {
    "groups": [
      {
        "group": "Getting Started",
        "pages": [
          "introduction",
          "installation/overview",
          "installation/world-installation",
          "installation/drop-in-merge"
        ]
      },
      {
        "group": "Cave Biomes",
        "pages": [
          "biomes/overview",
          "biomes/honey-grotto",
          "biomes/frozen-caverns",
          "biomes/molten-passages",
          "biomes/fungal-undergrowth",
          "biomes/amethyst-hollow",
          "biomes/subterranean-mesa",
          "biomes/terracotta-caves",
          "biomes/sandy-chambers",
          "biomes/overgrown-dugout",
          "biomes/marble-mines",
          "biomes/granite-mines",
          "biomes/andesite-mines",
          "biomes/diorite-mines",
          "biomes/coral-coves"
        ]
      },
      {
        "group": "Configuration",
        "pages": [
          "configuration/overview",
          "configuration/biome-distribution",
          "configuration/strata-layers",
          "configuration/disabling-biomes"
        ]
      },
      {
        "group": "Advanced",
        "pages": [
          "advanced/cave-carving-system",
          "advanced/custom-features",
          "advanced/palette-system"
        ]
      },
      {
        "group": "Resources",
        "pages": [
          "resources/troubleshooting",
          "resources/faq"
        ]
      }
    ]
  }
}
